<?xml version="1.0" encoding="UTF-8" standalone="no"?><ContractNotice xmlns="urn:oasis:names:specification:ubl:schema:xsd:ContractNotice-2" xmlns:cac="urn:oasis:names:specification:ubl:schema:xsd:CommonAggregateComponents-2" xmlns:cbc="urn:oasis:names:specification:ubl:schema:xsd:CommonBasicComponents-2" xmlns:efac="http://data.europa.eu/p27/eforms-ubl-extension-aggregate-components/1" xmlns:efbc="http://data.europa.eu/p27/eforms-ubl-extension-basic-components/1" xmlns:efext="http://data.europa.eu/p27/eforms-ubl-extensions/1" xmlns:ext="urn:oasis:names:specification:ubl:schema:xsd:CommonExtensionComponents-2"><ext:UBLExtensions><ext:UBLExtension><ext:ExtensionContent><efext:EformsExtension><efac:NoticeSubType><cbc:SubTypeCode listName="notice-subtype">16</cbc:SubTypeCode></efac:NoticeSubType><efac:Organizations><efac:Organization><efbc:GroupLeadIndicator>false</efbc:GroupLeadIndicator><efbc:AcquiringCPBIndicator>false</efbc:AcquiringCPBIndicator><efbc:AwardingCPBIndicator>false</efbc:AwardingCPBIndicator><efac:Company><cbc:WebsiteURI>http://www.bundesimmobilien.de</cbc:WebsiteURI><cac:PartyIdentification><cbc:ID schemeName="organization">ORG-0001</cbc:ID></cac:PartyIdentification><cac:PartyName><cbc:Name languageID="DEU">Bundesanstalt für Immobilienaufgaben</cbc:Name></cac:PartyName><cac:PostalAddress><cbc:CityName>Bonn</cbc:CityName><cbc:PostalZone>53119</cbc:PostalZone><cbc:CountrySubentityCode listName="nuts-lvl3">DEA22</cbc:CountrySubentityCode><cac:Country><cbc:IdentificationCode listName="eforms-country">DEU</cbc:IdentificationCode></cac:Country></cac:PostalAddress><cac:PartyLegalEntity><cbc:CompanyID>991-80032-33</cbc:CompanyID></cac:PartyLegalEntity><cac:Contact><cbc:Name>Verdingungsstelle</cbc:Name><cbc:Telephone>000</cbc:Telephone><cbc:ElectronicMail>Verdingung@bundesimmobilien.de</cbc:ElectronicMail></cac:Contact></efac:Company></efac:Organization><efac:Organization><efbc:GroupLeadIndicator>false</efbc:GroupLeadIndicator><efbc:AcquiringCPBIndicator>false</efbc:AcquiringCPBIndicator><efbc:AwardingCPBIndicator>false</efbc:AwardingCPBIndicator><efac:Company><cac:PartyIdentification><cbc:ID schemeName="organization">ORG-0002</cbc:ID></cac:PartyIdentification><cac:PartyName><cbc:Name languageID="DEU">Bundeskartellamt, Vergabekammern des Bundes</cbc:Name></cac:PartyName><cac:PostalAddress><cbc:CityName>Bonn</cbc:CityName><cbc:PostalZone>53113</cbc:PostalZone><cbc:CountrySubentityCode listName="nuts-lvl3">DEA22</cbc:CountrySubentityCode><cac:Country><cbc:IdentificationCode listName="eforms-country">DEU</cbc:IdentificationCode></cac:Country></cac:PostalAddress><cac:PartyLegalEntity><cbc:CompanyID>000</cbc:CompanyID></cac:PartyLegalEntity><cac:Contact><cbc:Telephone>000</cbc:Telephone><cbc:ElectronicMail>vk@bundeskartellamt.bund.de</cbc:ElectronicMail></cac:Contact></efac:Company></efac:Organization><efac:Organization><efac:Company><cac:PartyIdentification><cbc:ID schemeName="organization">ORG-0003</cbc:ID></cac:PartyIdentification><cac:PartyName><cbc:Name languageID="DEU">Beschaffungsamt des BMI</cbc:Name></cac:PartyName><cac:PostalAddress><cbc:CityName>Bonn</cbc:CityName><cbc:PostalZone>53119</cbc:PostalZone><cbc:CountrySubentityCode listName="nuts">DEA22</cbc:CountrySubentityCode><cac:Country><cbc:IdentificationCode listName="country">DEU</cbc:IdentificationCode></cac:Country></cac:PostalAddress><cac:PartyLegalEntity><cbc:CompanyID schemeID="002">994-DOEVD-83</cbc:CompanyID></cac:PartyLegalEntity><cac:Contact><cbc:Telephone>+49228996100</cbc:Telephone><cbc:ElectronicMail>esender_hub@bescha.bund.de</cbc:ElectronicMail></cac:Contact></efac:Company></efac:Organization></efac:Organizations><efac:Publication><efbc:NoticePublicationID schemeName="ojs-notice-id">00165900-2024</efbc:NoticePublicationID><efbc:GazetteID schemeName="ojs-id">57/2024</efbc:GazetteID><efbc:PublicationDate>2024-03-20Z</efbc:PublicationDate></efac:Publication></efext:EformsExtension></ext:ExtensionContent></ext:UBLExtension></ext:UBLExtensions><cbc:UBLVersionID>2.3</cbc:UBLVersionID><cbc:CustomizationID>eforms-sdk-1.7</cbc:CustomizationID><cbc:ID schemeName="notice-id">f5171623-aa9d-4d00-8bc4-e7c3abbd06b2</cbc:ID><cbc:ContractFolderID>20690635-2761-4b9e-aea4-d44edfa3e9b5</cbc:ContractFolderID><cbc:IssueDate>2024-03-19+01:00</cbc:IssueDate><cbc:IssueTime>11:10:33+01:00</cbc:IssueTime><cbc:VersionID>02</cbc:VersionID><cbc:RequestedPublicationDate>2024-03-19+01:00</cbc:RequestedPublicationDate><cbc:RegulatoryDomain>32014L0024</cbc:RegulatoryDomain><cbc:NoticeTypeCode listName="competition">cn-standard</cbc:NoticeTypeCode><cbc:NoticeLanguageCode listName="eu-official-language">DEU</cbc:NoticeLanguageCode><cac:ContractingParty><cac:ContractingPartyType><cbc:PartyTypeCode listName="buyer-legal-type">body-pl-cga</cbc:PartyTypeCode></cac:ContractingPartyType><cac:ContractingActivity><cbc:ActivityTypeCode listName="authority-activity">gen-pub</cbc:ActivityTypeCode></cac:ContractingActivity><cac:Party><cac:PartyIdentification><cbc:ID schemeName="organization">ORG-0001</cbc:ID></cac:PartyIdentification><cac:ServiceProviderParty><cbc:ServiceTypeCode listName="organisation-role">ted-esen</cbc:ServiceTypeCode><cac:Party><cac:PartyIdentification><cbc:ID schemeName="organization">ORG-0003</cbc:ID></cac:PartyIdentification></cac:Party></cac:ServiceProviderParty></cac:Party></cac:ContractingParty><cac:TenderingTerms><cac:ProcurementLegislationDocumentReference><cbc:ID>vgv</cbc:ID></cac:ProcurementLegislationDocumentReference><cac:TendererQualificationRequest><cac:SpecificTendererRequirement><cbc:TendererRequirementTypeCode listName="exclusion-ground">nati-ground</cbc:TendererRequirementTypeCode><cbc:Description languageID="DEU">Zwingende und fakultative Ausschlussgründe nach § 123 und § 124 GWB; 
Es wird auf Anlage B-03 Ziffer 3 verwiesen.</cbc:Description></cac:SpecificTendererRequirement><cac:SpecificTendererRequirement><cbc:TendererRequirementTypeCode listName="exclusion-ground">nati-ground</cbc:TendererRequirementTypeCode><cbc:Description languageID="DEU">Bezug des Bieters zu Russland; 
Es wird auf Anlage B-03 Ziffer 4 verwiesen.</cbc:Description></cac:SpecificTendererRequirement><cac:SpecificTendererRequirement><cbc:TendererRequirementTypeCode listName="exclusion-ground">nati-ground</cbc:TendererRequirementTypeCode><cbc:Description languageID="DEU">Überschreitung der maximalen Stundenrichtleistungen:
Es wird auf Anlage A-01 Ziffer 15b verwiesen.</cbc:Description></cac:SpecificTendererRequirement></cac:TendererQualificationRequest></cac:TenderingTerms><cac:TenderingProcess><cbc:ProcedureCode listName="procurement-procedure-type">open</cbc:ProcedureCode></cac:TenderingProcess><cac:ProcurementProject><cbc:ID schemeName="InternalID">VOEK 097-24</cbc:ID><cbc:Name languageID="DEU">Offenes Verfahren (EU-weit) zur Vergabe von Gebäudereinigungsleistungen (Unter-haltsreinigungsleistungen) für eine Dienstliegenschaft in Hamburg, 
Bundesanstalt für Immobilienaufgaben, Direktion Rostock (VOEK 097-24)</cbc:Name><cbc:Description languageID="DEU">Gebäudereinigung:
- Unterhaltsreinigungsleistungen
- Grund-/Intensivreinigung
- Bedarfsleistungen</cbc:Description><cbc:ProcurementTypeCode listName="eforms-contract-nature">services</cbc:ProcurementTypeCode><cbc:Note languageID="DEU">1) Das am 08.04.2022 veröffentlichte 5. EU-Sanktionspaket im Zusammenhang mit dem Angriffskrieg Russlands auf die Ukraine hat unmittelbare Auswirkungen auf die Vergabe öffentlicher Aufträge und Konzessionen - z. T. auch außerhalb der EU-Vergaberichtlinien. Verboten sind demnach seit dem 09.04.2022 sowohl Auftragsvergaben an Unternehmen mit Bezug zu Russland im Sinne der EU-Richtlinie 833/2014 (Russland-Embargoverordnung) als auch eine Beteiligung solcher Unternehmen am Auftrag als Unterauftragnehmer, Lieferanten oder im Zusammenhang mit der Erbringung des Eignungsnachweises, soweit auf diese zugezogenen Unternehmen mehr als 10% des Auftragswertes entfallen. Um die Einhaltung dieser Vorgaben prüfen zu können, sind vom Bieter bei Ziffer II.4. der Anlage B-03 „Bieterauskunft Eignungskriterien“ Erklärungen abzugeben und diese zusammen mit den Angebotsunterlagen vor Ablauf der 
Angebotsfrist über die e-Vergabe-Plattform einzureichen.
2) Ortsbesichtigungen sind freiwillig, werden aber dringend empfohlen. Ortsbesichtigungen 
erfolgen nur nach Absprache.  Besichtigungstermine sind vorab mit der für das Objekt zuständigen Ansprechperson zu vereinbaren. Ortsbesichtigungen können nur im Zeitraum vom 
22.04.2024 bis 26.04.2024 durchgeführt werden. Die Besichtigungstermine müssen bis spätestens 5 Werktage vorher vereinbart werden. Die Zuweisung eines Termins erfolgt in der Reihenfolge des Eingangs der Anmeldungen. Nur von der Auftraggeberin bestätigte Termine werden durchgeführt. Die Vertreter des Teilnehmers müssen bei der Ortsbesichtigung ein gültiges amtliches Ausweisdokument mit sich führen. Fragen zu den Vergabeunterlagen werden im Termin zur Ortsbesichtigung nicht beantwortet.

3.1) Anfragen zu den Vergabeunterlagen sind unter Verwendung des beigefügten Formblatts „FB Frage-Antwort“ ausschließlich über die e-Vergabe-Plattform (www.evergabe-online.de) einzureichen.

Anfragen, die auf anderem Weg übermittelt werden, können nicht berücksichtigt werden. Anfragen werden grundsätzlich nur beantwortet, wenn sie bis spätestens 30.04.2024 bei der e-Vergabe-Plattform eingehen. Die Auftraggeberin wird den Teilnehmern rechtzeitig angeforderte Auskünfte erteilen, soweit aus der Fragestellung die Relevanz für die Erstellung der Angebote ersichtlich ist.

3.2) Bei technischen Fragen zur e-Vergabe-Plattform wenden Sie sich bitte an den e-Vergabe HelpDesk:
Telefon: +49 (0) 22899 610 1234
E-Mail: ticket@bescha.bund.de
Geschäftszeiten: Montag bis Donnerstag: 08:00 bis 16:00 Uhr, Freitag: 08:00 bis 14:00 Uhr</cbc:Note><cac:MainCommodityClassification><cbc:ItemClassificationCode listName="cpv">90911200</cbc:ItemClassificationCode></cac:MainCommodityClassification><cac:RealizedLocation><cac:Address><cbc:StreetName>Hauptzollamt Hamburg, Sachgebiet C,	Ausschläger Elbdeich 2, 20539 Hamburg</cbc:StreetName><cbc:CityName>Hamburg</cbc:CityName><cbc:PostalZone>20539</cbc:PostalZone><cbc:CountrySubentityCode listName="nuts-lvl3">DE600</cbc:CountrySubentityCode><cac:Country><cbc:IdentificationCode listName="eforms-country">DEU</cbc:IdentificationCode></cac:Country></cac:Address></cac:RealizedLocation></cac:ProcurementProject><cac:ProcurementProjectLot><cbc:ID schemeName="Lot">LOT-0001</cbc:ID><cac:TenderingTerms><ext:UBLExtensions><ext:UBLExtension><ext:ExtensionContent><efext:EformsExtension><efac:SelectionCriteria><cbc:CriterionTypeCode listName="selection-criterion">tp-abil</cbc:CriterionTypeCode><cbc:Description languageID="DEU">Leistungsbezogene Angaben zum Unternehmen - Seit wann ist das Unternehmen in der ausgeschriebenen Leistungsart tätig? - Beschäftigtenzahl des gesamten Unternehmens - Anzahl der Beschäftigten, bezogen auf die ausgeschriebene Leistungsart - Anzahl der geringfügig Beschäftigten, bezogen auf die ausgeschriebene Leistungsart. 
Eigenerklärung zum Qualitätsmanagement Eigenerklärung zum praktizierten Qualitätsmanagement, insbesondere Angaben zur Dokumentation von Reinigungsleistungen, beispielsweise durch Angabe einer ISOZertifizierung nach DIN EN ISO 9001 ff oder nach 14001 ff bzw. einer gleichwertigen Bescheinigung. 
Referenzen Eigenerklärung zu mindestens 3 vergleichbaren Referenzen für die Leistungsart von mindestens 2 verschiedenen Referenzgebern aus dem Zeitraum der letzten drei Jahre mit Angabe von: Art des Referenzobjektes, Ausführungsort (Anschrift) des Referenzobjektes, jährlicher Leistungsumfang in qm, Leistungszeitraum, Leistungsart, Name des Auftraggebers und Ansprechperson mit Telefonnummer und E-Mail Adresse. Vergleichbar sind Referenzen, deren Gegenstand dem Ausschreibungsgegenstand zumindest nahekommt. Die Referenzen müssen im technischen oder organisatorischen Bereich einen gleich hohen oder höheren Schwierigkeitsgrad aufweisen und einen tragfähigen Rückschluss auf die Leistungsfähigkeit des Bieters für die ausgeschriebene Leistung ermöglichen. Erreicht die umfangreichste der drei genannten Referenzen nicht 75 % ausgeschriebenen Leistungsvolumens oder mindestens eine der beiden weiteren Referenzen nicht 50 % des ausgeschriebenen Volumens, wird der Bieter aufgefordert, die Vergleichbarkeit näher zu erläutern.</cbc:Description></efac:SelectionCriteria><efac:SelectionCriteria><cbc:CriterionTypeCode listName="selection-criterion">ef-stand</cbc:CriterionTypeCode><cbc:Description languageID="DEU">Eigenerklärung zur Betriebshaftpflichtversicherung Die Betriebshaftpflichtversicherung hat mindestens folgende Deckungssummen (bei mindestens zweifacher Maximierung im Versicherungsjahr) pro Schadensfall aufzuweisen: Personenschäden 2 Mio. €, Sachschäden 2 
Mio. €, Vermögensschäden 500.000 €, Schlüsselschäden 250.000 €. Sollte die Betriebshaftpflichtversicherung vorgenannten Deckungssummen derzeit nicht erreichen oder noch keine Betriebshaftpflichtversicherung abgeschlossen sein, so ist der Bieter verpflichtet, im Falle der Zuschlagserteilung die Deckungssummen entsprechend zu erhöhen bzw. abzuschließen. 
Eigenerklärung zum Umsatz Eigenerklärung zum Gesamtumsatz des Unternehmens sowie zum Umsatz bezüglich der ausgeschriebenen Leistungsart, jeweils bezogen auf die letzten 3 abgeschlossenen Geschäftsjahre.</cbc:Description></efac:SelectionCriteria><efac:StrategicProcurement><efbc:ApplicableLegalBasis listName="cvd-scope">false</efbc:ApplicableLegalBasis></efac:StrategicProcurement></efext:EformsExtension></ext:ExtensionContent></ext:UBLExtension></ext:UBLExtensions><cbc:VariantConstraintCode listName="permission">not-allowed</cbc:VariantConstraintCode><cbc:FundingProgramCode listName="eu-funded">no-eu-funds</cbc:FundingProgramCode><cbc:MultipleTendersCode listName="permission">not-allowed</cbc:MultipleTendersCode><cac:CallForTendersDocumentReference><cbc:ID>VOEK 097-24</cbc:ID><cbc:DocumentType>non-restricted-document</cbc:DocumentType><cbc:LanguageID>DEU</cbc:LanguageID><cac:Attachment><cac:ExternalReference><cbc:URI>https://www.evergabe-online.de/tenderdocuments.html?id=620560</cbc:URI></cac:ExternalReference></cac:Attachment></cac:CallForTendersDocumentReference><cac:TendererQualificationRequest><cac:SpecificTendererRequirement><cbc:TendererRequirementTypeCode listName="reserved-procurement">none</cbc:TendererRequirementTypeCode></cac:SpecificTendererRequirement></cac:TendererQualificationRequest><cac:TendererQualificationRequest><cac:SpecificTendererRequirement><cbc:TendererRequirementTypeCode listName="missing-info-submission">late-all</cbc:TendererRequirementTypeCode><cbc:Description languageID="DEU">Die Nachforderung, Vervollständigung oder Korrektur von Unterlagen, Eigenerklärungen, Angaben, Bescheinigungen und Nachweisen richtet sich nach dem § 56 VgV. Hierbei setzt die Auftraggeberin eine angemessene Frist und übt ihr Ermessen unter Beachtung des Gleichbehandlungsgrundsatzes aus. Einen Anspruch auf Nachforderung haben die Bieter nicht.</cbc:Description></cac:SpecificTendererRequirement></cac:TendererQualificationRequest><cac:ContractExecutionRequirement><cbc:ExecutionRequirementCode listName="nda">true</cbc:ExecutionRequirementCode><cbc:Description languageID="DEU">Der Auftragnehmer hat das Reinigungspersonal zur Verschwiegenheit zu verpflichten und von diesem vor dem erstmaligen Arbeitseinsatz folgende schriftliche Erklärung zu verlangen:
"Ich bestätige hierdurch, dass es mir untersagt ist, Einsicht in Schriftstücke aller Art, Akten usw. zu nehmen, die in den Räumen der zu reinigenden Dienstgebäude aufbewahrt werden und/oder davon Abschriften, Fotokopien und dergleichen zu fertigen. Ich bin von meinem Arbeitgeber darüber belehrt worden, dass ich bei Verstoß gegen dieses Verbot mit meiner fristlosen Entlassung zu rechnen habe; eine eventuelle Verpflichtung zum Schadenersatz bleibt hiervon unberührt."
Diese Erklärung ist jährlich zu wiederholen. Der Auftragnehmer hat der Auftraggeberin auf Verlangen Kopien dieser schriftlichen Erklärungen zu überlassen.
Der Auftragnehmer hat die Verschwiegenheit seiner Arbeitnehmer sicherzustellen.</cbc:Description></cac:ContractExecutionRequirement><cac:ContractExecutionRequirement><cbc:ExecutionRequirementCode listName="reserved-execution">no</cbc:ExecutionRequirementCode></cac:ContractExecutionRequirement><cac:ContractExecutionRequirement><cbc:ExecutionRequirementCode listName="einvoicing">required</cbc:ExecutionRequirementCode></cac:ContractExecutionRequirement><cac:ContractExecutionRequirement><cbc:ExecutionRequirementCode listName="ecatalog-submission">not-allowed</cbc:ExecutionRequirementCode></cac:ContractExecutionRequirement><cac:AwardingTerms><cac:AwardingCriterion><cac:SubordinateAwardingCriterion><cbc:AwardingCriterionTypeCode listName="award-criterion-type">price</cbc:AwardingCriterionTypeCode><cbc:Description languageID="DEU">Wertungspreis:
Als Wertungspreis wird die Summe der jährlichen Gesamtnettopreise einschließlich aller Preise für die Bedarfsleistungen laut Preisblatt gewertet. Das Angebot mit dem niedrigsten Wer-tungspreis erhält die maximal mögliche Punktzahl. Die anderen Angebote erhalten nach Maßgabe der folgenden Formel entsprechend weniger Punkte:
Punktzahl (zu bewertendes Angebot) = maximale Punktzahl x (niedrigster Wertungspreis / zu bewertender Wertungspreis). Die resultierende Punktwerte werden auf eine Nachkommastelle kaufmännisch gerechnet.
Gewichtung: 70 %</cbc:Description></cac:SubordinateAwardingCriterion><cac:SubordinateAwardingCriterion><cbc:AwardingCriterionTypeCode listName="award-criterion-type">quality</cbc:AwardingCriterionTypeCode><cbc:Description languageID="DEU">Angebotene Reinigungsstunden:
Als angebotene Reinigungsstunden wird die Summe der jährlichen Reinigungsstunden der Raumgruppen/Reinigungsbereiche laut Preisblatt gewertet. Das Angebot mit den meisten angebo-tenen Reinigungsstunden erhält die maximal mögliche Punktzahl. Die anderen Angebote erhalten nach Maßgabe der folgenden Formel entsprechend weniger Punkte:
Punktzahl (zu bewertendes Angebot) = maximale Punktzahl x (zu bewertende angebotene Anzahl an Reinigungsstunden / höchste angebotene Anzahl an Reinigungsstunden).
Gewichtung: 30 %</cbc:Description></cac:SubordinateAwardingCriterion></cac:AwardingCriterion></cac:AwardingTerms><cac:TenderValidityPeriod><cbc:DurationMeasure unitCode="DAY">170</cbc:DurationMeasure></cac:TenderValidityPeriod><cac:AppealTerms><cac:PresentationPeriod><cbc:Description languageID="DEU">Genaue Angaben zu den Fristen für die Einlegung von Rechtsbehelfen: Es gelten die Regelungen der §§ 155 ff. GWB. Insbesondere ist § 160 Abs. 3 GWB zu beachten: Verstöße gegen das
Vergaberecht , die aus der Bekanntmachung oder den Vergabeunterlagen hervorgehen, müssen bis zum Ablauf der Angebotsfrist gerügt werden. Der Antrag auf Einleitung eines Nachprüfungsverfahrens muss innerhalb einer Frist von 15 Kalendertagen nach Eingang der Mitteilung der Auftraggeberin, einer Rüge nicht abhelfen zu wollen, eingereicht werden (vlg.
§ 160 Abs. 3 S. 1 Nr. 4 GWB).</cbc:Description></cac:PresentationPeriod><cac:AppealReceiverParty><cac:PartyIdentification><cbc:ID schemeName="organization">ORG-0002</cbc:ID></cac:PartyIdentification></cac:AppealReceiverParty></cac:AppealTerms><cac:Language><cbc:ID>DEU</cbc:ID></cac:Language><cac:PostAwardProcess><cbc:ElectronicOrderUsageIndicator>true</cbc:ElectronicOrderUsageIndicator><cbc:ElectronicPaymentUsageIndicator>true</cbc:ElectronicPaymentUsageIndicator></cac:PostAwardProcess><cac:SecurityClearanceTerm><cbc:Code listName="required">false</cbc:Code></cac:SecurityClearanceTerm></cac:TenderingTerms><cac:TenderingProcess><ext:UBLExtensions><ext:UBLExtension><ext:ExtensionContent><efext:EformsExtension><efbc:ProcedureRelaunchIndicator>false</efbc:ProcedureRelaunchIndicator></efext:EformsExtension></ext:ExtensionContent></ext:UBLExtension></ext:UBLExtensions><cbc:SubmissionMethodCode listName="esubmission">required</cbc:SubmissionMethodCode><cbc:GovernmentAgreementConstraintIndicator>true</cbc:GovernmentAgreementConstraintIndicator><cac:TenderSubmissionDeadlinePeriod><cbc:EndDate>2024-05-14+02:00</cbc:EndDate><cbc:EndTime>12:00:00+02:00</cbc:EndTime></cac:TenderSubmissionDeadlinePeriod><cac:AdditionalInformationRequestPeriod><cbc:EndDate>2024-04-30+02:00</cbc:EndDate></cac:AdditionalInformationRequestPeriod><cac:OpenTenderEvent><cbc:OccurrenceDate>2024-05-15+02:00</cbc:OccurrenceDate><cbc:OccurrenceTime>00:00:00+02:00</cbc:OccurrenceTime><cbc:Description languageID="DEU">Die Teilnahme der Bieter am Eröffnungstermin ist nicht gestattet. Die Zuschlagserteilung erfolgt auf elektronischem Weg.</cbc:Description><cac:OccurenceLocation><cbc:Description languageID="DEU">Berlin</cbc:Description></cac:OccurenceLocation></cac:OpenTenderEvent><cac:AuctionTerms><cbc:AuctionConstraintIndicator>false</cbc:AuctionConstraintIndicator></cac:AuctionTerms><cac:ContractingSystem><cbc:ContractingSystemTypeCode listName="framework-agreement">none</cbc:ContractingSystemTypeCode></cac:ContractingSystem><cac:ContractingSystem><cbc:ContractingSystemTypeCode listName="dps-usage">none</cbc:ContractingSystemTypeCode></cac:ContractingSystem></cac:TenderingProcess><cac:ProcurementProject><cbc:ID schemeName="InternalID">VOEK 097-24</cbc:ID><cbc:Name languageID="DEU">Offenes Verfahren (EU-weit) zur Vergabe von Gebäudereinigungsleistungen (Unter-haltsreinigungsleistungen) für eine Dienstliegenschaft in Hamburg, 
Bundesanstalt für Immobilienaufgaben, Direktion Rostock (VOEK 097-24)</cbc:Name><cbc:Description languageID="DEU">- Unterhaltsreinigung
3.378,69 m² Grundfläche, 882.988,24 m² jährl. Reinigungsfläche
- Grund-/ Intensivreinigung
- Bedarfsleistungen</cbc:Description><cbc:ProcurementTypeCode listName="contract-nature">services</cbc:ProcurementTypeCode><cbc:Note languageID="DEU">#Besonders geeignet für:freelance#, #Besonders geeignet für:selbst#, #Besonders geeignet für:startup#</cbc:Note><cbc:SMESuitableIndicator>true</cbc:SMESuitableIndicator><cac:ProcurementAdditionalType><cbc:ProcurementTypeCode listName="strategic-procurement">none</cbc:ProcurementTypeCode></cac:ProcurementAdditionalType><cac:MainCommodityClassification><cbc:ItemClassificationCode listName="cpv">90911200</cbc:ItemClassificationCode></cac:MainCommodityClassification><cac:RealizedLocation><cac:Address><cbc:StreetName>Hauptzollamt Hamburg, Sachgebiet C,	Ausschläger Elbdeich 2, 20539 Hamburg</cbc:StreetName><cbc:CityName>Hamburg</cbc:CityName><cbc:PostalZone>20539</cbc:PostalZone><cbc:CountrySubentityCode listName="nuts-lvl3">DE600</cbc:CountrySubentityCode><cac:Country><cbc:IdentificationCode listName="eforms-country">DEU</cbc:IdentificationCode></cac:Country></cac:Address></cac:RealizedLocation><cac:PlannedPeriod><cbc:StartDate>2024-11-01+01:00</cbc:StartDate><cbc:EndDate>2028-10-31+01:00</cbc:EndDate></cac:PlannedPeriod><cac:ContractExtension><cbc:OptionsDescription languageID="DEU">1.	Die erstmalige Leistungserbringung erfolgt zum 01.11.2024
2.	Das Vertragsverhältnis wird zunächst für die Dauer von 4 Jahren bis zum 31.10.2028 abgeschlossen. Es verlängert sich, sofern nicht die Auftraggeberin mit einer Frist von 6 Monaten vor Ablauf der Vertragslaufzeit schriftlich widerspricht, jeweils um ein weiteres Jahr. Die entsprechende Wider-spruchsfrist für den Auftragnehmer beträgt 9 Monate vor Ablauf der Vertragslaufzeit. Das verlängerte Vertragsverhältnis kann von der Auftraggeberin mit einer Frist von 3 Monaten jeweils zum Ende eines Kalendermonats gekündigt werden. Die maximale Vertragsdauer beträgt 6 Jahre (bis 31.10.2030).</cbc:OptionsDescription></cac:ContractExtension></cac:ProcurementProject></cac:ProcurementProjectLot></ContractNotice>