<?xml version="1.0" encoding="UTF-8" standalone="no"?><ContractNotice xmlns="urn:oasis:names:specification:ubl:schema:xsd:ContractNotice-2" xmlns:cac="urn:oasis:names:specification:ubl:schema:xsd:CommonAggregateComponents-2" xmlns:cbc="urn:oasis:names:specification:ubl:schema:xsd:CommonBasicComponents-2" xmlns:efac="http://data.europa.eu/p27/eforms-ubl-extension-aggregate-components/1" xmlns:efbc="http://data.europa.eu/p27/eforms-ubl-extension-basic-components/1" xmlns:efext="http://data.europa.eu/p27/eforms-ubl-extensions/1" xmlns:ext="urn:oasis:names:specification:ubl:schema:xsd:CommonExtensionComponents-2" xmlns:xsi="http://www.w3.org/2001/XMLSchema-instance">
   <ext:UBLExtensions>
      <ext:UBLExtension>
         <ext:ExtensionContent>
            <efext:EformsExtension>
               <efac:NoticeSubType>
                  <cbc:SubTypeCode listName="notice-subtype">16</cbc:SubTypeCode>
               </efac:NoticeSubType>
               <efac:Organizations>
                  <efac:Organization>
                     <efbc:AcquiringCPBIndicator>false</efbc:AcquiringCPBIndicator>
                     <efbc:AwardingCPBIndicator>false</efbc:AwardingCPBIndicator>
                     <efac:Company>
                        <cbc:WebsiteURI>http://www.ausschreibungen.ls.brandenburg.de</cbc:WebsiteURI>
                        <cac:PartyIdentification>
                           <cbc:ID schemeName="organization">ORG-7001</cbc:ID>
                        </cac:PartyIdentification>
                        <cac:PartyName>
                           <cbc:Name languageID="DEU">Landesbetrieb Straßenwesen Brandenburg Dienststätte Potsdam</cbc:Name>
                        </cac:PartyName>
                        <cac:PostalAddress>
                           <cbc:StreetName>Steinstraße 104 - 106, Haus 14c</cbc:StreetName>
                           <cbc:CityName>Potsdam</cbc:CityName>
                           <cbc:PostalZone>14480</cbc:PostalZone>
                           <cbc:CountrySubentityCode listName="nuts">DE404</cbc:CountrySubentityCode>
                           <cac:Country>
                              <cbc:IdentificationCode listName="country">DEU</cbc:IdentificationCode>
                           </cac:Country>
                        </cac:PostalAddress>
                        <cac:PartyLegalEntity>
                           <cbc:CompanyID>122200</cbc:CompanyID>
                        </cac:PartyLegalEntity>
                        <cac:Contact>
                           <cbc:Name>Landesbetrieb Straßenwesen Brandenburg, Dienststätte Potsdam</cbc:Name>
                           <cbc:Telephone>+49 3342-249-1364</cbc:Telephone>
                           <cbc:ElectronicMail>annegret.biniok@ls.brandenburg.de</cbc:ElectronicMail>
                        </cac:Contact>
                     </efac:Company>
                  </efac:Organization>
                  <efac:Organization>
                     <efac:Company>
                        <cbc:WebsiteURI>http://mwe.brandenburg.de</cbc:WebsiteURI>
                        <cac:PartyIdentification>
                           <cbc:ID schemeName="organization">ORG-7004</cbc:ID>
                        </cac:PartyIdentification>
                        <cac:PartyName>
                           <cbc:Name languageID="DEU">Vergabekammern des Landes Brandenburg beim Ministerium für Wirtschaft und Energie</cbc:Name>
                        </cac:PartyName>
                        <cac:PostalAddress>
                           <cbc:StreetName>Heinrich-Mann-Allee 107</cbc:StreetName>
                           <cbc:CityName>Potsdam</cbc:CityName>
                           <cbc:PostalZone>14473</cbc:PostalZone>
                           <cbc:CountrySubentityCode listName="nuts">DE404</cbc:CountrySubentityCode>
                           <cac:Country>
                              <cbc:IdentificationCode listName="country">DEU</cbc:IdentificationCode>
                           </cac:Country>
                        </cac:PostalAddress>
                        <cac:PartyLegalEntity>
                           <cbc:CompanyID>T:03318661719</cbc:CompanyID>
                        </cac:PartyLegalEntity>
                        <cac:Contact>
                           <cbc:Telephone>+49 3318661610</cbc:Telephone>
                           <cbc:ElectronicMail>poststelle.krypto@mwe.brandenburg.de</cbc:ElectronicMail>
                        </cac:Contact>
                     </efac:Company>
                  </efac:Organization>
                  <efac:Organization>
                     <efac:Company>
                        <cac:PartyIdentification>
                           <cbc:ID schemeName="organization">ORG-7005</cbc:ID>
                        </cac:PartyIdentification>
                        <cac:PartyName>
                           <cbc:Name languageID="DEU">Landesbetrieb Straßenwesen Brandenburg Dienststätte Potsdam</cbc:Name>
                        </cac:PartyName>
                        <cac:PostalAddress>
                           <cbc:StreetName>Steinstraße 104 - 106, Haus 14C</cbc:StreetName>
                           <cbc:CityName>Potsdam</cbc:CityName>
                           <cbc:PostalZone>14480</cbc:PostalZone>
                           <cbc:CountrySubentityCode listName="nuts">DE404</cbc:CountrySubentityCode>
                           <cac:Country>
                              <cbc:IdentificationCode listName="country">DEU</cbc:IdentificationCode>
                           </cac:Country>
                        </cac:PostalAddress>
                        <cac:PartyLegalEntity>
                           <cbc:CompanyID>122200</cbc:CompanyID>
                        </cac:PartyLegalEntity>
                        <cac:Contact>
                           <cbc:Telephone>+49 33422491364</cbc:Telephone>
                           <cbc:ElectronicMail>annegret.biniok@ls.brandenburg.de</cbc:ElectronicMail>
                        </cac:Contact>
                     </efac:Company>
                  </efac:Organization>
                  <efac:Organization>
                     <efac:Company>
                        <cac:PartyIdentification>
                           <cbc:ID schemeName="organization">ORG-7006</cbc:ID>
                        </cac:PartyIdentification>
                        <cac:PartyName>
                           <cbc:Name languageID="DEU">Ministerium für Infrastruktur und Landesplanung, Abt. 4, Ref. 47</cbc:Name>
                        </cac:PartyName>
                        <cac:PostalAddress>
                           <cbc:StreetName>Henning-von-Tresckow-Straße 2 - 8</cbc:StreetName>
                           <cbc:CityName>Potsdam</cbc:CityName>
                           <cbc:PostalZone>14467</cbc:PostalZone>
                           <cbc:CountrySubentityCode listName="nuts">DE404</cbc:CountrySubentityCode>
                           <cac:Country>
                              <cbc:IdentificationCode listName="country">DEU</cbc:IdentificationCode>
                           </cac:Country>
                        </cac:PostalAddress>
                        <cac:PartyLegalEntity>
                           <cbc:CompanyID>122200</cbc:CompanyID>
                        </cac:PartyLegalEntity>
                        <cac:Contact>
                           <cbc:Telephone>+49 3318668430</cbc:Telephone>
                           <cbc:ElectronicMail>poststelle@mil.brandenburg.de</cbc:ElectronicMail>
                        </cac:Contact>
                     </efac:Company>
                  </efac:Organization>
               <efac:Organization><efac:Company><cac:PartyIdentification><cbc:ID schemeName="organization">ORG-7007</cbc:ID></cac:PartyIdentification><cac:PartyName><cbc:Name languageID="DEU">Datenservice Öffentlicher Einkauf (in Verantwortung des Beschaffungsamts des BMI)</cbc:Name></cac:PartyName><cac:PostalAddress><cbc:CityName>Bonn</cbc:CityName><cbc:PostalZone>53119</cbc:PostalZone><cbc:CountrySubentityCode listName="nuts">DEA22</cbc:CountrySubentityCode><cac:Country><cbc:IdentificationCode listName="country">DEU</cbc:IdentificationCode></cac:Country></cac:PostalAddress><cac:PartyLegalEntity><cbc:CompanyID schemeID="002">0204:994-DOEVD-83</cbc:CompanyID></cac:PartyLegalEntity><cac:Contact><cbc:Telephone>+49228996100</cbc:Telephone><cbc:ElectronicMail>noreply.esender_hub@bescha.bund.de</cbc:ElectronicMail></cac:Contact></efac:Company></efac:Organization></efac:Organizations>
            <efac:Publication><efbc:NoticePublicationID schemeName="ojs-notice-id">00314268-2025</efbc:NoticePublicationID><efbc:GazetteID schemeName="ojs-id">93/2025</efbc:GazetteID><efbc:PublicationDate>2025-05-15+02:00</efbc:PublicationDate></efac:Publication></efext:EformsExtension>
         </ext:ExtensionContent>
      </ext:UBLExtension>
   </ext:UBLExtensions>
   <cbc:UBLVersionID>2.3</cbc:UBLVersionID>
   <cbc:CustomizationID>eforms-sdk-1.12</cbc:CustomizationID>
   <cbc:ProfileID>eforms-sdk-1.12</cbc:ProfileID>
   <cbc:ID schemeName="notice-id">58f8874d-b5c3-42d9-83e4-591b01270fe0</cbc:ID>
   <cbc:ContractFolderID>4f951351-1d5b-4400-9605-6f8b76cbc2cf</cbc:ContractFolderID>
   <cbc:IssueDate>2025-05-14+02:00</cbc:IssueDate>
   <cbc:IssueTime>08:06:03+02:00</cbc:IssueTime>
   <cbc:VersionID>01</cbc:VersionID>
   <cbc:RequestedPublicationDate>2025-05-14+02:00</cbc:RequestedPublicationDate>
   <cbc:RegulatoryDomain>32014L0024</cbc:RegulatoryDomain>
   <cbc:NoticeTypeCode listName="competition">cn-standard</cbc:NoticeTypeCode>
   <cbc:NoticeLanguageCode listName="language">DEU</cbc:NoticeLanguageCode>
   <cac:ContractingParty>
      <cbc:BuyerProfileURI>http://www.ausschreibungen.ls.brandenburg.de</cbc:BuyerProfileURI>
      <cac:ContractingPartyType>
         <cbc:PartyTypeCode listName="buyer-legal-type">ra</cbc:PartyTypeCode>
      </cac:ContractingPartyType>
      <cac:ContractingActivity>
         <cbc:ActivityTypeCode listName="authority-activity">gen-pub</cbc:ActivityTypeCode>
      </cac:ContractingActivity>
      <cac:Party>
         <cac:PartyIdentification>
            <cbc:ID schemeName="organization">ORG-7001</cbc:ID>
         </cac:PartyIdentification>
      <cac:ServiceProviderParty><cbc:ServiceTypeCode listName="organisation-role">ted-esen</cbc:ServiceTypeCode><cac:Party><cac:PartyIdentification><cbc:ID schemeName="organization">ORG-7007</cbc:ID></cac:PartyIdentification></cac:Party></cac:ServiceProviderParty></cac:Party>
   </cac:ContractingParty>
   <cac:TenderingTerms>
      <cac:ProcurementLegislationDocumentReference>
         <cbc:ID>vob-a-eu</cbc:ID>
      </cac:ProcurementLegislationDocumentReference>
      <cac:TendererQualificationRequest>
         <cac:SpecificTendererRequirement>
            <cbc:TendererRequirementTypeCode listName="exclusion-grounds-source">epo-notice</cbc:TendererRequirementTypeCode>
         </cac:SpecificTendererRequirement>
         <cac:SpecificTendererRequirement>
            <cbc:TendererRequirementTypeCode listName="exclusion-grounds-source">epo-procurement-document</cbc:TendererRequirementTypeCode>
         </cac:SpecificTendererRequirement>
      </cac:TendererQualificationRequest>
      <cac:TendererQualificationRequest>
         <cac:SpecificTendererRequirement>
            <cbc:TendererRequirementTypeCode listName="exclusion-ground">exg-sitn-other</cbc:TendererRequirementTypeCode>
            <cbc:Description languageID="DEU">§ 124 GWB Abs. 1 Nr. 2</cbc:Description>
         </cac:SpecificTendererRequirement>
         <cac:SpecificTendererRequirement>
            <cbc:TendererRequirementTypeCode listName="exclusion-ground">exg-natl-bre-nat-law</cbc:TendererRequirementTypeCode>
            <cbc:Description languageID="DEU">Es gelten die Ausschlussgründe nach den §§ 123 und 124 GWB sowie nach den §§ 42 und 57 VgV.</cbc:Description>
         </cac:SpecificTendererRequirement>
      </cac:TendererQualificationRequest>
   </cac:TenderingTerms>
   <cac:TenderingProcess>
      <cbc:ProcedureCode listName="procurement-procedure-type">open</cbc:ProcedureCode>
      <cac:ProcessJustification>
         <cbc:ProcessReasonCode listName="accelerated-procedure">false</cbc:ProcessReasonCode>
      </cac:ProcessJustification>
   </cac:TenderingProcess>
   <cac:ProcurementProject>
      <cbc:ID>P-2025-0035</cbc:ID>
      <cbc:Name languageID="DEU">B1 BÜ Beseitigung Wust - FL Straßenbau</cbc:Name>
      <cbc:Description languageID="DEU">B1 BÜ Beseitigung Wust - FL Straßenbau</cbc:Description>
      <cbc:ProcurementTypeCode listName="contract-nature">works</cbc:ProcurementTypeCode>
      <cbc:Note languageID="DEU">Elektronisch übermittelte Angebote sind mit einer fortgeschrittenen elektronischen oder mit einer qualifizierten elektronischen Signatur nach dem Signaturgesetz zu versehen und über das auf der Internetseite http://www.ausschreibungen.ls.brandenburg.de zum Download bereitgestellte Bietercockpit auf http://www.ausschreibungen.ls.brandenburg.de einzureichen.</cbc:Note>
      <cac:MainCommodityClassification>
         <cbc:ItemClassificationCode listName="cpv">45000000</cbc:ItemClassificationCode>
      </cac:MainCommodityClassification>
      <cac:AdditionalCommodityClassification>
         <cbc:ItemClassificationCode listName="cpv">45233130</cbc:ItemClassificationCode>
      </cac:AdditionalCommodityClassification>
      <cac:RealizedLocation>
         <cac:Address>
            <cbc:StreetName>B1</cbc:StreetName>
            <cbc:CityName>Brandenburg (Havel)</cbc:CityName>
            <cbc:PostalZone>14770</cbc:PostalZone>
            <cbc:CountrySubentityCode listName="nuts">DE401</cbc:CountrySubentityCode>
            <cac:Country>
               <cbc:IdentificationCode listName="country">DEU</cbc:IdentificationCode>
            </cac:Country>
         </cac:Address>
      </cac:RealizedLocation>
   </cac:ProcurementProject>
   <cac:ProcurementProjectLot>
      <cbc:ID schemeName="Lot">LOT-0000</cbc:ID>
      <cac:TenderingTerms>
         <ext:UBLExtensions>
            <ext:UBLExtension>
               <ext:ExtensionContent>
                  <efext:EformsExtension>
                     <efac:StrategicProcurement>
                        <efbc:ApplicableLegalBasis listName="cvd-scope">false</efbc:ApplicableLegalBasis>
                     </efac:StrategicProcurement>
                  </efext:EformsExtension>
               </ext:ExtensionContent>
            </ext:UBLExtension>
         </ext:UBLExtensions>
         <cbc:VariantConstraintCode listName="permission">not-allowed</cbc:VariantConstraintCode>
         <cbc:FundingProgramCode listName="eu-funded">no-eu-funds</cbc:FundingProgramCode>
         <cbc:RequiredCurriculaCode listName="requirement-stage">not-requ</cbc:RequiredCurriculaCode>
         <cbc:RecurringProcurementIndicator>false</cbc:RecurringProcurementIndicator>
         <cbc:MultipleTendersCode listName="permission">not-allowed</cbc:MultipleTendersCode>
         <cac:CallForTendersDocumentReference>
            <ext:UBLExtensions>
               <ext:UBLExtension>
                  <ext:ExtensionContent>
                     <efext:EformsExtension>
                        <efac:OfficialLanguages>
                           <cac:Language>
                              <cbc:ID>DEU</cbc:ID>
                           </cac:Language>
                        </efac:OfficialLanguages>
                     </efext:EformsExtension>
                  </ext:ExtensionContent>
               </ext:UBLExtension>
            </ext:UBLExtensions>
            <cbc:ID>TenderDoc</cbc:ID>
            <cbc:DocumentType>non-restricted-document</cbc:DocumentType>
            <cac:Attachment>
               <cac:ExternalReference>
                  <cbc:URI>https://www.ausschreibungen.ls.brandenburg.de/NetServer/TenderingProcedureDetails?function=_Details&amp;TenderOID=54321-Tender-1969f6503a0-676d112d9eff06fd</cbc:URI>
               </cac:ExternalReference>
            </cac:Attachment>
         </cac:CallForTendersDocumentReference>
         <cac:TendererQualificationRequest>
            <cac:SpecificTendererRequirement>
               <cbc:TendererRequirementTypeCode listName="selection-criteria-source">epo-procurement-document</cbc:TendererRequirementTypeCode>
            </cac:SpecificTendererRequirement>
         </cac:TendererQualificationRequest>
         <cac:TendererQualificationRequest>
            <cac:SpecificTendererRequirement>
               <cbc:TendererRequirementTypeCode listName="missing-info-submission">late-all</cbc:TendererRequirementTypeCode>
               <cbc:Description languageID="DEU">Unterlagen werden nachgefordert</cbc:Description>
            </cac:SpecificTendererRequirement>
         </cac:TendererQualificationRequest>
         <cac:TendererQualificationRequest>
            <cac:SpecificTendererRequirement>
               <cbc:TendererRequirementTypeCode listName="reserved-procurement">none</cbc:TendererRequirementTypeCode>
            </cac:SpecificTendererRequirement>
         </cac:TendererQualificationRequest>
         <cac:ContractExecutionRequirement>
            <cbc:ExecutionRequirementCode listName="reserved-execution">no</cbc:ExecutionRequirementCode>
         </cac:ContractExecutionRequirement>
         <cac:ContractExecutionRequirement>
            <cbc:ExecutionRequirementCode listName="conditions">performance</cbc:ExecutionRequirementCode>
            <cbc:Description languageID="DEU">Zum Nachweis der beruflichen und technischen
Leistungsfähigkeit kann der öffentliche Auftraggeber je nach
Art, Menge oder Umfang oder Verwendungszweck der
ausgeschriebenen Leistung verlangen:
a) Angaben über die Ausführung von Leistungen in den letzten
bis zu fünf abgeschlossenen Kalenderjahren, die mit der zu
vergebenden Leistung vergleichbar sind, wobei für die
wichtigsten Bauleistungen Bescheinigungen über die
ordnungsgemäße Ausführung und das Ergebnis beizufügen
sind.
b) Angabe der technischen Fachkräfte oder der technischen
Stellen, unabhängig davon, ob sie seinem Unternehmen
angehören oder nicht, und zwar insbesondere derjenigen, die
mit der Qualitätskontrolle beauftragt sind, und
derjenigen, über die der Unternehmer für die Errichtung des
Bauwerks verfügt;
Möglicherweise geforderte Mindeststandards:
- Nachweis der Qualifikation MVAS
- Unterlagen gemäß Vordruck vorzulegende Unterlagen</cbc:Description>
         </cac:ContractExecutionRequirement>
         <cac:ContractExecutionRequirement>
            <cbc:ExecutionRequirementCode listName="einvoicing">allowed</cbc:ExecutionRequirementCode>
         </cac:ContractExecutionRequirement>
         <cac:ContractExecutionRequirement>
            <cbc:ExecutionRequirementCode listName="ecatalog-submission">not-allowed</cbc:ExecutionRequirementCode>
         </cac:ContractExecutionRequirement>
         <cac:AwardingTerms>
            <cac:AwardingCriterion>
               <cac:SubordinateAwardingCriterion>
                  <ext:UBLExtensions>
                     <ext:UBLExtension>
                        <ext:ExtensionContent>
                           <efext:EformsExtension>
                              <efac:AwardCriterionParameter>
                                 <efbc:ParameterCode listName="number-weight">per-exa</efbc:ParameterCode>
                                 <efbc:ParameterNumeric>100.00</efbc:ParameterNumeric>
                              </efac:AwardCriterionParameter>
                           </efext:EformsExtension>
                        </ext:ExtensionContent>
                     </ext:UBLExtension>
                  </ext:UBLExtensions>
                  <cbc:AwardingCriterionTypeCode listName="award-criterion-type">price</cbc:AwardingCriterionTypeCode>
                  <cbc:Name languageID="DEU">Preis</cbc:Name>
                  <cbc:Description languageID="DEU">Preis</cbc:Description>
               </cac:SubordinateAwardingCriterion>
            </cac:AwardingCriterion>
         </cac:AwardingTerms>
         <cac:AdditionalInformationParty>
            <cac:PartyIdentification>
               <cbc:ID schemeName="organization">ORG-7001</cbc:ID>
            </cac:PartyIdentification>
         </cac:AdditionalInformationParty>
         <cac:TenderRecipientParty>
            <cbc:EndpointID>http://www.ausschreibungen.ls.brandenburg.de</cbc:EndpointID>
            <cac:PartyIdentification>
               <cbc:ID schemeName="organization">ORG-7001</cbc:ID>
            </cac:PartyIdentification>
         </cac:TenderRecipientParty>
         <cac:TenderValidityPeriod>
            <cbc:DurationMeasure unitCode="MONTH">2</cbc:DurationMeasure>
         </cac:TenderValidityPeriod>
         <cac:AppealTerms>
            <cac:PresentationPeriod>
               <cbc:Description languageID="DEU">Auf die Unzulässigkeit eines Nachprüfungsantrages nach Ablauf der Frist des § 160 Abs. 3 Nr. 4 GWB (15 Tage nach Eingang des Nichtabhilfebescheides auf eine Rüge) wird hingewiesen.</cbc:Description>
            </cac:PresentationPeriod>
            <cac:AppealInformationParty>
               <cac:PartyIdentification>
                  <cbc:ID schemeName="organization">ORG-7005</cbc:ID>
               </cac:PartyIdentification>
            </cac:AppealInformationParty>
            <cac:AppealReceiverParty>
               <cac:PartyIdentification>
                  <cbc:ID schemeName="organization">ORG-7004</cbc:ID>
               </cac:PartyIdentification>
            </cac:AppealReceiverParty>
            <cac:MediationParty>
               <cac:PartyIdentification>
                  <cbc:ID schemeName="organization">ORG-7006</cbc:ID>
               </cac:PartyIdentification>
            </cac:MediationParty>
         </cac:AppealTerms>
         <cac:Language>
            <cbc:ID>DEU</cbc:ID>
         </cac:Language>
         <cac:PostAwardProcess>
            <cbc:ElectronicOrderUsageIndicator>true</cbc:ElectronicOrderUsageIndicator>
            <cbc:ElectronicPaymentUsageIndicator>false</cbc:ElectronicPaymentUsageIndicator>
         </cac:PostAwardProcess>
      </cac:TenderingTerms>
      <cac:TenderingProcess>
         <cbc:SubmissionMethodCode listName="esubmission">allowed</cbc:SubmissionMethodCode>
         <cbc:GovernmentAgreementConstraintIndicator>true</cbc:GovernmentAgreementConstraintIndicator>
         <cac:TenderSubmissionDeadlinePeriod>
            <cbc:EndDate>2025-06-18+02:00</cbc:EndDate>
            <cbc:EndTime>09:00:00+02:00</cbc:EndTime>
         </cac:TenderSubmissionDeadlinePeriod>
         <cac:OpenTenderEvent>
            <cbc:OccurrenceDate>2025-06-18+02:00</cbc:OccurrenceDate>
            <cbc:OccurrenceTime>09:00:00+02:00</cbc:OccurrenceTime>
            <cbc:Description languageID="DEU">elektronische Angebotseröffnung - keine Zulassung von Bietervertretern</cbc:Description>
            <cac:OccurenceLocation>
               <cbc:Description languageID="DEU">Landesbetrieb Straßenwesen Brandenburg Dienststätte Potsdam
Steinstraße 104 bis 106, Haus 14c
14480 Potsdam</cbc:Description>
            </cac:OccurenceLocation>
         </cac:OpenTenderEvent>
         <cac:AuctionTerms>
            <cbc:AuctionConstraintIndicator>false</cbc:AuctionConstraintIndicator>
         </cac:AuctionTerms>
         <cac:ContractingSystem>
            <cbc:ContractingSystemTypeCode listName="framework-agreement">none</cbc:ContractingSystemTypeCode>
         </cac:ContractingSystem>
         <cac:ContractingSystem>
            <cbc:ContractingSystemTypeCode listName="dps-usage">none</cbc:ContractingSystemTypeCode>
         </cac:ContractingSystem>
      </cac:TenderingProcess>
      <cac:ProcurementProject>
         <cbc:ID>LOT-0000</cbc:ID>
         <cbc:Name languageID="DEU">B1 BÜ Beseitigung Wust - FL Straßenbau</cbc:Name>
         <cbc:Description languageID="DEU">ca. 8.940 m2	Provisorische Asphaltbefestigungen herstellen, rückbauen
ca. 36.150 m2	Asphalt fräsen (Verwertungsklasse A), verwerten
ca. 1.600 m2	Asphalt feinfräsen (Verwertungsklasse A), verwerten
ca. 13.130 m2	Asphalt fräsen (gefährlicher Abfall), lagern, entsorgen
ca. 1.050 m2	TS mit hydr. Bindem. aufn. (= RC3), lagern, verwerten
ca. 350 m2	Betondecke aufnehmen, teilweise lagern, verwerten
ca. 260 m2	Betonsteinpflasterdecke aufnehmen, verwerten
ca. 330 m	Bordstein aufnehmen und verwerten (Naturstein/Beton)
ca. 645 m3	SoB aufnehmen (= RC3), lagern, verwerten
ca. 645 m3	Bankettmaterial aufnehmen (= RC3), lagern, verwerten
ca. 2.500 m3	SoB aufnehmen (gefährlicher Abfall), lagern, entsorgen
ca. 550 m3	Bankettmaterial aufnehmen (gef. Abfall), lagern, ents.
ca. 370 m3	Packlage aufnehmen (gef. Abfall), lagern, entsorgen
ca. 640 m2	Markierung entfernen 
ca. 520 m	Fahrzeugrückhaltesystem abbauen und verwerten
ca. 57 m	Rohrleitung (bis DN600) rückbauen und entsorgen
ca. 19.900m2	Asphalttragschicht herstellen (unterschiedliche Dicken)
ca. 13.210 m2	Asphaltbinderschicht herstellen
ca. 12.750 m2	Splittmastixdecke herstellen
ca. 670 m2	Gussasphaltdecke herstellen
ca. 7.860 m2	Asphaltbetondecke herstellen
ca. 3.540 m2	Asphalttragdeckschicht herstellen
ca. 28.880 m2	Schottertragschicht herstellen (unterschiedliche Dicken)
ca. 1.955 t	Schottertragschicht herstellen (unterschiedliche Dicken)
ca. 4.660 t	Schicht aus frostunempfindlichen Material herstellen
ca. 6.850 m2	Bankettbefestigungen herstellen
ca. 48.440	m2	Planum herstellen
ca. 14.800	m3	Oberboden aufnehmen (= BM-F3), verwerten
ca. 745  m3	Oberboden aufnehmen (= BM-F3), lagern, verwerten
ca. 6.800 m3	Oberboden liefern und andecken (unterschiedl. Dicken)
ca. 15.430	m2	Erosionsschutzmatten verlegen
ca. 2.640 m	Mulde herstellen (unterschiedliche Tiefen und Breiten)
ca. 6.070 m3	Boden aufnehmen (= BM-F3), verwerten
ca. 3.745 m3	Boden aufnehmen (= BM-F3), lagern, verwerten
ca. 2.230 m3	Boden aufnehmen (gefährlicher Abfall), lagern, entsorgen
ca. 2.500 m3	Boden aufnehmen, lagern, wieder einbauen
ca. 2.640 m3	Bodenverbesserung mit Boden ausführen
ca. 7.300 m3	Bodenverbesserung mit Schicht ohne Bindemittel ausf.
ca. 600 m	Abtreppung am vorhandenen Straßendamm herstellen
ca. 49.450 m3	F1-Boden liefern und einbauen (BM-0)
ca. 39.700 m3	F1-Boden liefern und einbauen (max. BM-F1 oder besser)
ca. 49.425 m2	Rasenansaat inkl. Saatgut liefern und Pflege
ca. 422 m2	Pflasterdecke gebunden aus Naturstein
ca. 127 m	Bordrinne gebunden aus Naturstein
ca. 110 m2	Pflasterdecke ungebunden aus Betonstein
ca. 134 m2	Plattendecke ungebunden aus Beton
ca. 61	m2	Decke aus Rasengitter ungebunden
ca. 1.345	m	Natursteinborde setzen (Flach- und Tiefborde)
ca. 44	m	Natursteinborde setzen (Kasseler Sonderbord)
ca. 440	m	Betonborde setzen (Tiefborde)
ca. 61	m2	Wasserdurchlässige Betontragschicht herstellen
ca. 93 m2	Betontragschicht herstellen (unterschiedliche Dicken)
ca. 465	m	Anschlussleitung DN150 herstellen (Kunststoff)
ca. 48	m	Abwasserdruckleitung herstellen
ca. 34,5	m	Durchlassrohr DN600 herstellen (Stahlbeton)
ca. 47	St	Straßenabläufe herstellen
  1	St	Pumpanlage herstellen
ca. 17	m	Winkelstützen (Bauhöhe 1,55 m) herstellen
ca. 583	m	Geländer (Anlehnung an RiZ Gel 7) herstellen
ca. 47	m	Maschendrahtzaun herstellen
ca. 82	m	Stahlgitterzaun herstellen
ca. 6	St	Tore Stahlgitterzaun herstellen
ca. 8 St	Beleuchtungsmaste stellen inklusive Erd- und Kabelbau
   1	St	Stallgebäude aus Holz (gefährlicher Abfall) abbrechen
ca. 1	t	Wellasbest aufnehmen und entsorgen
ca. 5.750	m	Freigabemarkierung (verschiedene Breiten) 
ca. 47	m	Gasleitungen aus Stahl rückbauen</cbc:Description>
         <cbc:ProcurementTypeCode listName="contract-nature">works</cbc:ProcurementTypeCode>
         <cbc:Note languageID="DEU">Eine Registrierung auf der Plattform ist freiwillig. Beim Unterlassen der freiwilligen Registrierung trägt das Unternehmen das Risiko, einen Teilnahmeantrag, eine Interessenbestätigung oder ein Angebot auf der Grundlage veralteter Vergabeunterlagen erstellt zu haben und daher im weiteren Verlauf vom Verfahren ausgeschlossen zu werden.</cbc:Note>
         <cbc:SMESuitableIndicator>false</cbc:SMESuitableIndicator>
         <cac:ProcurementAdditionalType>
            <cbc:ProcurementTypeCode listName="strategic-procurement">none</cbc:ProcurementTypeCode>
         </cac:ProcurementAdditionalType>
         <cac:MainCommodityClassification>
            <cbc:ItemClassificationCode listName="cpv">45000000</cbc:ItemClassificationCode>
         </cac:MainCommodityClassification>
         <cac:AdditionalCommodityClassification>
            <cbc:ItemClassificationCode listName="cpv">45233130</cbc:ItemClassificationCode>
         </cac:AdditionalCommodityClassification>
         <cac:PlannedPeriod>
            <cbc:StartDate>2025-09-29+02:00</cbc:StartDate>
            <cbc:EndDate>2027-04-30+02:00</cbc:EndDate>
         </cac:PlannedPeriod>
      </cac:ProcurementProject>
   </cac:ProcurementProjectLot>
</ContractNotice>