<?xml version="1.0" encoding="UTF-8" standalone="no"?><ContractAwardNotice xmlns="urn:oasis:names:specification:ubl:schema:xsd:ContractAwardNotice-2" xmlns:cac="urn:oasis:names:specification:ubl:schema:xsd:CommonAggregateComponents-2" xmlns:cbc="urn:oasis:names:specification:ubl:schema:xsd:CommonBasicComponents-2" xmlns:efac="http://data.europa.eu/p27/eforms-ubl-extension-aggregate-components/1" xmlns:efbc="http://data.europa.eu/p27/eforms-ubl-extension-basic-components/1" xmlns:efext="http://data.europa.eu/p27/eforms-ubl-extensions/1" xmlns:ext="urn:oasis:names:specification:ubl:schema:xsd:CommonExtensionComponents-2" xmlns:xsi="http://www.w3.org/2001/XMLSchema-instance"><ext:UBLExtensions><ext:UBLExtension><ext:ExtensionContent><efext:EformsExtension><efac:NoticeResult><cbc:TotalAmount currencyID="EUR">0</cbc:TotalAmount><efac:LotResult><cbc:ID schemeName="result">RES-0001</cbc:ID><cbc:TenderResultCode listName="winner-selection-status">selec-w</cbc:TenderResultCode><efac:LotTender><cbc:ID schemeName="tender">TEN-0001</cbc:ID></efac:LotTender><efac:ReceivedSubmissionsStatistics><efbc:StatisticsCode listName="received-submission-type">tenders</efbc:StatisticsCode><efbc:StatisticsNumeric>7</efbc:StatisticsNumeric></efac:ReceivedSubmissionsStatistics><efac:ReceivedSubmissionsStatistics><efbc:StatisticsCode listName="received-submission-type">t-sme</efbc:StatisticsCode><efbc:StatisticsNumeric>3</efbc:StatisticsNumeric></efac:ReceivedSubmissionsStatistics><efac:ReceivedSubmissionsStatistics><efbc:StatisticsCode listName="received-submission-type">t-oth-eea</efbc:StatisticsCode><efbc:StatisticsNumeric>0</efbc:StatisticsNumeric></efac:ReceivedSubmissionsStatistics><efac:ReceivedSubmissionsStatistics><efbc:StatisticsCode listName="received-submission-type">t-no-eea</efbc:StatisticsCode><efbc:StatisticsNumeric>0</efbc:StatisticsNumeric></efac:ReceivedSubmissionsStatistics><efac:ReceivedSubmissionsStatistics><efbc:StatisticsCode listName="received-submission-type">t-esubm</efbc:StatisticsCode><efbc:StatisticsNumeric>7</efbc:StatisticsNumeric></efac:ReceivedSubmissionsStatistics><efac:SettledContract><cbc:ID schemeName="contract">CON-0001</cbc:ID></efac:SettledContract><efac:TenderLot><cbc:ID schemeName="Lot">LOT-0001</cbc:ID></efac:TenderLot></efac:LotResult><efac:LotResult><cbc:ID schemeName="result">RES-0002</cbc:ID><cbc:TenderResultCode listName="winner-selection-status">selec-w</cbc:TenderResultCode><efac:LotTender><cbc:ID schemeName="tender">TEN-0002</cbc:ID></efac:LotTender><efac:ReceivedSubmissionsStatistics><efbc:StatisticsCode listName="received-submission-type">tenders</efbc:StatisticsCode><efbc:StatisticsNumeric>3</efbc:StatisticsNumeric></efac:ReceivedSubmissionsStatistics><efac:ReceivedSubmissionsStatistics><efbc:StatisticsCode listName="received-submission-type">t-sme</efbc:StatisticsCode><efbc:StatisticsNumeric>1</efbc:StatisticsNumeric></efac:ReceivedSubmissionsStatistics><efac:ReceivedSubmissionsStatistics><efbc:StatisticsCode listName="received-submission-type">t-oth-eea</efbc:StatisticsCode><efbc:StatisticsNumeric>0</efbc:StatisticsNumeric></efac:ReceivedSubmissionsStatistics><efac:ReceivedSubmissionsStatistics><efbc:StatisticsCode listName="received-submission-type">t-no-eea</efbc:StatisticsCode><efbc:StatisticsNumeric>0</efbc:StatisticsNumeric></efac:ReceivedSubmissionsStatistics><efac:ReceivedSubmissionsStatistics><efbc:StatisticsCode listName="received-submission-type">t-esubm</efbc:StatisticsCode><efbc:StatisticsNumeric>3</efbc:StatisticsNumeric></efac:ReceivedSubmissionsStatistics><efac:SettledContract><cbc:ID schemeName="contract">CON-0002</cbc:ID></efac:SettledContract><efac:TenderLot><cbc:ID schemeName="Lot">LOT-0002</cbc:ID></efac:TenderLot></efac:LotResult><efac:LotResult><cbc:ID schemeName="result">RES-0003</cbc:ID><cbc:TenderResultCode listName="winner-selection-status">selec-w</cbc:TenderResultCode><efac:LotTender><cbc:ID schemeName="tender">TEN-0003</cbc:ID></efac:LotTender><efac:ReceivedSubmissionsStatistics><efbc:StatisticsCode listName="received-submission-type">tenders</efbc:StatisticsCode><efbc:StatisticsNumeric>6</efbc:StatisticsNumeric></efac:ReceivedSubmissionsStatistics><efac:ReceivedSubmissionsStatistics><efbc:StatisticsCode listName="received-submission-type">t-sme</efbc:StatisticsCode><efbc:StatisticsNumeric>2</efbc:StatisticsNumeric></efac:ReceivedSubmissionsStatistics><efac:ReceivedSubmissionsStatistics><efbc:StatisticsCode listName="received-submission-type">t-oth-eea</efbc:StatisticsCode><efbc:StatisticsNumeric>0</efbc:StatisticsNumeric></efac:ReceivedSubmissionsStatistics><efac:ReceivedSubmissionsStatistics><efbc:StatisticsCode listName="received-submission-type">t-no-eea</efbc:StatisticsCode><efbc:StatisticsNumeric>0</efbc:StatisticsNumeric></efac:ReceivedSubmissionsStatistics><efac:ReceivedSubmissionsStatistics><efbc:StatisticsCode listName="received-submission-type">t-esubm</efbc:StatisticsCode><efbc:StatisticsNumeric>6</efbc:StatisticsNumeric></efac:ReceivedSubmissionsStatistics><efac:SettledContract><cbc:ID schemeName="contract">CON-0003</cbc:ID></efac:SettledContract><efac:TenderLot><cbc:ID schemeName="Lot">LOT-0003</cbc:ID></efac:TenderLot></efac:LotResult><efac:LotTender><cbc:ID schemeName="tender">TEN-0001</cbc:ID><efbc:TenderVariantIndicator>false</efbc:TenderVariantIndicator><cac:LegalMonetaryTotal><cbc:PayableAmount currencyID="EUR">1</cbc:PayableAmount></cac:LegalMonetaryTotal><efac:SubcontractingTerm><efbc:TermCode listName="applicability">no</efbc:TermCode></efac:SubcontractingTerm><efac:TenderingParty><cbc:ID schemeName="tendering-party">TPA-0001</cbc:ID></efac:TenderingParty><efac:TenderLot><cbc:ID schemeName="Lot">LOT-0001</cbc:ID></efac:TenderLot><efac:TenderReference><cbc:ID>Los 1 Wilhelm-Bracke-Gesamtschule und GS Rheinring</cbc:ID></efac:TenderReference></efac:LotTender><efac:LotTender><cbc:ID schemeName="tender">TEN-0002</cbc:ID><efbc:TenderVariantIndicator>false</efbc:TenderVariantIndicator><cac:LegalMonetaryTotal><cbc:PayableAmount currencyID="EUR">1</cbc:PayableAmount></cac:LegalMonetaryTotal><efac:SubcontractingTerm><efbc:TermCode listName="applicability">no</efbc:TermCode></efac:SubcontractingTerm><efac:TenderingParty><cbc:ID schemeName="tendering-party">TPA-0002</cbc:ID></efac:TenderingParty><efac:TenderLot><cbc:ID schemeName="Lot">LOT-0002</cbc:ID></efac:TenderLot><efac:TenderReference><cbc:ID>Los 2 GS und HS Pestalozzistraße und GS Bültenweg</cbc:ID></efac:TenderReference></efac:LotTender><efac:LotTender><cbc:ID schemeName="tender">TEN-0003</cbc:ID><efbc:TenderVariantIndicator>false</efbc:TenderVariantIndicator><cac:LegalMonetaryTotal><cbc:PayableAmount currencyID="EUR">1</cbc:PayableAmount></cac:LegalMonetaryTotal><efac:SubcontractingTerm><efbc:TermCode listName="applicability">no</efbc:TermCode></efac:SubcontractingTerm><efac:TenderingParty><cbc:ID schemeName="tendering-party">TPA-0002</cbc:ID></efac:TenderingParty><efac:TenderLot><cbc:ID schemeName="Lot">LOT-0003</cbc:ID></efac:TenderLot><efac:TenderReference><cbc:ID>Los 3 IGS Heidberg und Gymnasium Raabeschule</cbc:ID></efac:TenderReference></efac:LotTender><efac:SettledContract><cbc:ID schemeName="contract">CON-0001</cbc:ID><cbc:IssueDate>2025-05-27+02:00</cbc:IssueDate><efac:ContractReference><cbc:ID>60-11-40-193-2024 Los 1</cbc:ID></efac:ContractReference><efac:LotTender><cbc:ID schemeName="tender">TEN-0001</cbc:ID></efac:LotTender></efac:SettledContract><efac:SettledContract><cbc:ID schemeName="contract">CON-0002</cbc:ID><cbc:IssueDate>2025-05-27+02:00</cbc:IssueDate><efac:ContractReference><cbc:ID>60-11-40-193-2024 Los 2</cbc:ID></efac:ContractReference><efac:LotTender><cbc:ID schemeName="tender">TEN-0002</cbc:ID></efac:LotTender></efac:SettledContract><efac:SettledContract><cbc:ID schemeName="contract">CON-0003</cbc:ID><cbc:IssueDate>2025-05-27+02:00</cbc:IssueDate><efac:ContractReference><cbc:ID>60-11-40-193-2024 Los 3</cbc:ID></efac:ContractReference><efac:LotTender><cbc:ID schemeName="tender">TEN-0003</cbc:ID></efac:LotTender></efac:SettledContract><efac:TenderingParty><cbc:ID schemeName="tendering-party">TPA-0001</cbc:ID><efac:Tenderer><cbc:ID schemeName="organization">ORG-0003</cbc:ID></efac:Tenderer></efac:TenderingParty><efac:TenderingParty><cbc:ID schemeName="tendering-party">TPA-0002</cbc:ID><efac:Tenderer><cbc:ID schemeName="organization">ORG-0004</cbc:ID></efac:Tenderer></efac:TenderingParty></efac:NoticeResult><efac:NoticeSubType><cbc:SubTypeCode listName="notice-subtype">29</cbc:SubTypeCode></efac:NoticeSubType><efac:Organizations><efac:Organization><efac:Company><cbc:WebsiteURI>https://www.deutsche-evergabe.de</cbc:WebsiteURI><cac:PartyIdentification><cbc:ID schemeName="organization">ORG-0001</cbc:ID></cac:PartyIdentification><cac:PartyName><cbc:Name languageID="DEU">Stadt Braunschweig Fachbereich Bauordnung und Zentrale Vergabestelle</cbc:Name></cac:PartyName><cac:PostalAddress><cbc:StreetName>Wendenring 1</cbc:StreetName><cbc:CityName>Braunschweig</cbc:CityName><cbc:PostalZone>38114</cbc:PostalZone><cbc:CountrySubentityCode listName="nuts">DE911</cbc:CountrySubentityCode><cac:Country><cbc:IdentificationCode listName="country">DEU</cbc:IdentificationCode></cac:Country></cac:PostalAddress><cac:PartyLegalEntity><cbc:CompanyID schemeID="EU">4346</cbc:CompanyID></cac:PartyLegalEntity><cac:Contact><cbc:Telephone>+49 5314702989</cbc:Telephone><cbc:ElectronicMail>beschaffung@braunschweig.de</cbc:ElectronicMail></cac:Contact></efac:Company></efac:Organization><efac:Organization><efac:Company><cac:PartyIdentification><cbc:ID schemeName="organization">ORG-0002</cbc:ID></cac:PartyIdentification><cac:PartyName><cbc:Name languageID="DEU">Vergabekammer Nds. beim Nds. Ministerium für Wirtschaft, Arbeit, Verkehr und Digitalisierung</cbc:Name></cac:PartyName><cac:PostalAddress><cbc:StreetName>Auf der Hude 2</cbc:StreetName><cbc:CityName>Lüneburg</cbc:CityName><cbc:PostalZone>21339</cbc:PostalZone><cbc:CountrySubentityCode listName="nuts">DE911</cbc:CountrySubentityCode><cac:Country><cbc:IdentificationCode listName="country">DEU</cbc:IdentificationCode></cac:Country></cac:PostalAddress><cac:PartyLegalEntity><cbc:CompanyID schemeID="EU">487856f3-d248-43ad-ace1-b1577fe99314</cbc:CompanyID></cac:PartyLegalEntity><cac:Contact><cbc:Telephone>+49 4131153306</cbc:Telephone><cbc:ElectronicMail>vergabekammer@mw.niedersachsen.de</cbc:ElectronicMail></cac:Contact></efac:Company></efac:Organization><efac:Organization><efac:Company><efbc:CompanySizeCode listName="economic-operator-size">medium</efbc:CompanySizeCode><cac:PartyIdentification><cbc:ID schemeName="organization">ORG-0003</cbc:ID></cac:PartyIdentification><cac:PartyName><cbc:Name languageID="DEU">biond GmbH</cbc:Name></cac:PartyName><cac:PostalAddress><cbc:CityName>Kassel</cbc:CityName><cbc:PostalZone>34123</cbc:PostalZone><cbc:CountrySubentityCode listName="nuts">DE731</cbc:CountrySubentityCode><cac:Country><cbc:IdentificationCode listName="country">DEU</cbc:IdentificationCode></cac:Country></cac:PostalAddress><cac:PartyLegalEntity><cbc:CompanyID schemeID="EU">DE279833632</cbc:CompanyID></cac:PartyLegalEntity><cac:Contact><cbc:Telephone>+4956150045610</cbc:Telephone><cbc:ElectronicMail>geniessen@biond.de</cbc:ElectronicMail></cac:Contact></efac:Company></efac:Organization><efac:Organization><efac:Company><efbc:CompanySizeCode listName="economic-operator-size">medium</efbc:CompanySizeCode><cac:PartyIdentification><cbc:ID schemeName="organization">ORG-0004</cbc:ID></cac:PartyIdentification><cac:PartyName><cbc:Name languageID="DEU">Bietergemeinschaft GFB Catering GmbH / Pausenfrisch GmbH &amp; Co. KG</cbc:Name></cac:PartyName><cac:PostalAddress><cbc:CityName>Leipzig</cbc:CityName><cbc:PostalZone>04178</cbc:PostalZone><cbc:CountrySubentityCode listName="nuts">DED51</cbc:CountrySubentityCode><cac:Country><cbc:IdentificationCode listName="country">DEU</cbc:IdentificationCode></cac:Country></cac:PostalAddress><cac:PartyLegalEntity><cbc:CompanyID schemeID="EU">DE143596371</cbc:CompanyID></cac:PartyLegalEntity><cac:Contact><cbc:Telephone>+493414482110</cbc:Telephone><cbc:ElectronicMail>ausschreibung@cc-leipzig.de</cbc:ElectronicMail></cac:Contact></efac:Company></efac:Organization><efac:Organization><efac:Company><cac:PartyIdentification><cbc:ID schemeName="organization">ORG-0005</cbc:ID></cac:PartyIdentification><cac:PartyName><cbc:Name languageID="DEU">Datenservice Öffentlicher Einkauf (in Verantwortung des Beschaffungsamts des BMI)</cbc:Name></cac:PartyName><cac:PostalAddress><cbc:CityName>Bonn</cbc:CityName><cbc:PostalZone>53119</cbc:PostalZone><cbc:CountrySubentityCode listName="nuts">DEA22</cbc:CountrySubentityCode><cac:Country><cbc:IdentificationCode listName="country">DEU</cbc:IdentificationCode></cac:Country></cac:PostalAddress><cac:PartyLegalEntity><cbc:CompanyID schemeID="002">0204:994-DOEVD-83</cbc:CompanyID></cac:PartyLegalEntity><cac:Contact><cbc:Telephone>+49228996100</cbc:Telephone><cbc:ElectronicMail>noreply.esender_hub@bescha.bund.de</cbc:ElectronicMail></cac:Contact></efac:Company></efac:Organization></efac:Organizations><efac:Publication><efbc:NoticePublicationID schemeName="ojs-notice-id">00400525-2025</efbc:NoticePublicationID><efbc:GazetteID schemeName="ojs-id">117/2025</efbc:GazetteID><efbc:PublicationDate>2025-06-20+02:00</efbc:PublicationDate></efac:Publication></efext:EformsExtension></ext:ExtensionContent></ext:UBLExtension></ext:UBLExtensions><cbc:UBLVersionID>2.3</cbc:UBLVersionID><cbc:CustomizationID>eforms-sdk-1.12</cbc:CustomizationID><cbc:ID schemeName="notice-id">7c6bd507-02a9-42a4-bf9c-0814fd29c4d1</cbc:ID><cbc:ContractFolderID>9139b080-e978-46b3-ad29-c3566cf40cd8</cbc:ContractFolderID><cbc:IssueDate>2025-06-19+02:00</cbc:IssueDate><cbc:IssueTime>08:04:00+02:00</cbc:IssueTime><cbc:VersionID>02</cbc:VersionID><cbc:RequestedPublicationDate>2025-06-19+02:00</cbc:RequestedPublicationDate><cbc:RegulatoryDomain>32014L0024</cbc:RegulatoryDomain><cbc:NoticeTypeCode listName="result">can-standard</cbc:NoticeTypeCode><cbc:NoticeLanguageCode>DEU</cbc:NoticeLanguageCode><cac:ContractingParty><cbc:BuyerProfileURI>https://www.deutsche-evergabe.de</cbc:BuyerProfileURI><cac:ContractingPartyType><cbc:PartyTypeCode listName="buyer-legal-type">la</cbc:PartyTypeCode></cac:ContractingPartyType><cac:ContractingActivity><cbc:ActivityTypeCode listName="authority-activity">gen-pub</cbc:ActivityTypeCode></cac:ContractingActivity><cac:Party><cac:PartyIdentification><cbc:ID schemeName="organization">ORG-0001</cbc:ID></cac:PartyIdentification><cac:ServiceProviderParty><cbc:ServiceTypeCode listName="organisation-role">ted-esen</cbc:ServiceTypeCode><cac:Party><cac:PartyIdentification><cbc:ID schemeName="organization">ORG-0005</cbc:ID></cac:PartyIdentification></cac:Party></cac:ServiceProviderParty></cac:Party></cac:ContractingParty><cac:TenderingTerms><cac:ProcurementLegislationDocumentReference><cbc:ID>vgv</cbc:ID></cac:ProcurementLegislationDocumentReference></cac:TenderingTerms><cac:TenderingProcess><cbc:ProcedureCode listName="procurement-procedure-type">open</cbc:ProcedureCode></cac:TenderingProcess><cac:ProcurementProject><cbc:ID>60-11-40-193-2024</cbc:ID><cbc:Name languageID="DEU">Mittagessenversorgung Braunschweiger Schulen</cbc:Name><cbc:Description languageID="DEU">Mittagessenversorgung Braunschweiger Schulen</cbc:Description><cbc:ProcurementTypeCode listName="contract-nature">services</cbc:ProcurementTypeCode><cac:MainCommodityClassification><cbc:ItemClassificationCode listName="cpv">55520000</cbc:ItemClassificationCode></cac:MainCommodityClassification><cac:RealizedLocation><cac:Address><cbc:CountrySubentityCode listName="nuts">DE911</cbc:CountrySubentityCode><cac:Country><cbc:IdentificationCode listName="country">DEU</cbc:IdentificationCode></cac:Country></cac:Address></cac:RealizedLocation><cac:RealizedLocation><cac:Address><cbc:CountrySubentityCode listName="nuts">DE911</cbc:CountrySubentityCode><cac:Country><cbc:IdentificationCode listName="country">DEU</cbc:IdentificationCode></cac:Country></cac:Address></cac:RealizedLocation><cac:RealizedLocation><cac:Address><cbc:CountrySubentityCode listName="nuts">DE911</cbc:CountrySubentityCode><cac:Country><cbc:IdentificationCode listName="country">DEU</cbc:IdentificationCode></cac:Country></cac:Address></cac:RealizedLocation><cac:RealizedLocation><cac:Address><cbc:CountrySubentityCode listName="nuts">DE911</cbc:CountrySubentityCode><cac:Country><cbc:IdentificationCode listName="country">DEU</cbc:IdentificationCode></cac:Country></cac:Address></cac:RealizedLocation></cac:ProcurementProject><cac:ProcurementProjectLot><cbc:ID schemeName="Lot">LOT-0001</cbc:ID><cac:TenderingTerms><ext:UBLExtensions><ext:UBLExtension><ext:ExtensionContent><efext:EformsExtension><efac:StrategicProcurement><efbc:ApplicableLegalBasis listName="cvd-scope">false</efbc:ApplicableLegalBasis></efac:StrategicProcurement></efext:EformsExtension></ext:ExtensionContent></ext:UBLExtension></ext:UBLExtensions><cbc:FundingProgramCode listName="eu-funded">no-eu-funds</cbc:FundingProgramCode><cac:AwardingTerms><cac:AwardingCriterion><cac:SubordinateAwardingCriterion><ext:UBLExtensions><ext:UBLExtension><ext:ExtensionContent><efext:EformsExtension><efac:AwardCriterionParameter><efbc:ParameterCode listName="number-weight">ord-imp</efbc:ParameterCode><efbc:ParameterNumeric>1</efbc:ParameterNumeric></efac:AwardCriterionParameter></efext:EformsExtension></ext:ExtensionContent></ext:UBLExtension></ext:UBLExtensions><cbc:AwardingCriterionTypeCode listName="award-criterion-type">price</cbc:AwardingCriterionTypeCode><cbc:Name languageID="DEU">Preis</cbc:Name><cbc:Description languageID="DEU">Preis</cbc:Description></cac:SubordinateAwardingCriterion></cac:AwardingCriterion></cac:AwardingTerms><cac:AdditionalInformationParty><cac:PartyIdentification><cbc:ID schemeName="organization">ORG-0001</cbc:ID></cac:PartyIdentification></cac:AdditionalInformationParty><cac:AppealTerms><cac:PresentationPeriod><cbc:Description languageID="DEU">(1) Etwaige Vergabeverstöße muss der Bewerber/Bieter gemäß § 160 Abs. 3 Nr. 1 GWB innerhalb von 10 Tagen nach Kenntnisnahme rügen.
(2) Verstöße gegen Vergabevorschriften, die aufgrund der Bekanntmachung erkennbar sind, sind nach § 160 Abs. 3 Nr. 2 GWB spätestens bis zum Ablauf der in der Bekanntmachung benannten Frist zur Abgabe der Bewerbung oder der Angebote gegenüber dem Auftraggeber zu rügen.
(3) Verstöße gegen Vergabevorschriften, die erst in den Vergabeunterlagen erkennbar sind, sind nach § 160 Abs. 3 Nr. 3 GWB spätestens bis zum Ablauf der Frist zur Bewerbungs- oder Angebotsabgabe gegenüber dem Auftraggeber zu rügen.
(4) Ein Vergabenachprüfungsantrag ist nach § 160 Abs. 3 Nr. 4 GWB innerhalb von 15 Kalendertagen nach der Mitteilung des Auftraggebers, einer Rüge nicht abhelfen zu wollen, bei der Vergabekammer einzureichen.</cbc:Description></cac:PresentationPeriod><cac:AppealReceiverParty><cac:PartyIdentification><cbc:ID schemeName="organization">ORG-0002</cbc:ID></cac:PartyIdentification></cac:AppealReceiverParty></cac:AppealTerms></cac:TenderingTerms><cac:TenderingProcess><cbc:GovernmentAgreementConstraintIndicator>true</cbc:GovernmentAgreementConstraintIndicator><cac:AuctionTerms><cbc:AuctionConstraintIndicator>false</cbc:AuctionConstraintIndicator></cac:AuctionTerms><cac:ContractingSystem><cbc:ContractingSystemTypeCode listName="framework-agreement">none</cbc:ContractingSystemTypeCode></cac:ContractingSystem><cac:ContractingSystem><cbc:ContractingSystemTypeCode listName="dps-usage">none</cbc:ContractingSystemTypeCode></cac:ContractingSystem></cac:TenderingProcess><cac:ProcurementProject><cbc:ID>0001</cbc:ID><cbc:Name languageID="DEU">Los 1 Wilhelm-Bracke-Gesamtschule und GS Rheinring</cbc:Name><cbc:Description languageID="DEU">Die/der AN sichert die Versorgung der Wilhelm-Bracke-Gesamtschule und der Grundschule Rheinring zu. Der Ort der Leistungserbringung ist die Küche mit Mensa in der Wilhelm-Bracke-Gesamtschule, Rheinring 12, 38120 Braunschweig. Diese be-findet sich im Schulgebäude der Wilhelm-Bracke-Gesamtschule.</cbc:Description><cbc:ProcurementTypeCode listName="contract-nature">services</cbc:ProcurementTypeCode><cac:ProcurementAdditionalType><cbc:ProcurementTypeCode listName="strategic-procurement">none</cbc:ProcurementTypeCode></cac:ProcurementAdditionalType><cac:MainCommodityClassification><cbc:ItemClassificationCode listName="cpv">55520000</cbc:ItemClassificationCode></cac:MainCommodityClassification><cac:RealizedLocation><cac:Address><cbc:CountrySubentityCode listName="nuts">DE911</cbc:CountrySubentityCode><cac:Country><cbc:IdentificationCode listName="country">DEU</cbc:IdentificationCode></cac:Country></cac:Address></cac:RealizedLocation><cac:ContractExtension><cbc:MaximumNumberNumeric>1</cbc:MaximumNumberNumeric><cac:Renewal><cac:Period><cbc:Description languageID="DEU">Eine Verlängerungsoption für den Zeitraum 19.08.2027 bis zum 18.07.2029 ist enthalten. Die Verlängerungsoption ist sechs Monate vor Ablauf des Vertrages durch die Stadt Braunschweig als Auftraggeberin (nachfolgend AG) zu ziehen und schriftlich mitzuteilen. Die Verlängerungsoption kann auch für einzelne Schulen in einem Los gezogen werden.</cbc:Description></cac:Period></cac:Renewal></cac:ContractExtension></cac:ProcurementProject></cac:ProcurementProjectLot><cac:ProcurementProjectLot><cbc:ID schemeName="Lot">LOT-0002</cbc:ID><cac:TenderingTerms><ext:UBLExtensions><ext:UBLExtension><ext:ExtensionContent><efext:EformsExtension><efac:StrategicProcurement><efbc:ApplicableLegalBasis listName="cvd-scope">false</efbc:ApplicableLegalBasis></efac:StrategicProcurement></efext:EformsExtension></ext:ExtensionContent></ext:UBLExtension></ext:UBLExtensions><cbc:FundingProgramCode listName="eu-funded">no-eu-funds</cbc:FundingProgramCode><cac:AwardingTerms><cac:AwardingCriterion><cac:SubordinateAwardingCriterion><ext:UBLExtensions><ext:UBLExtension><ext:ExtensionContent><efext:EformsExtension><efac:AwardCriterionParameter><efbc:ParameterCode listName="number-weight">ord-imp</efbc:ParameterCode><efbc:ParameterNumeric>1</efbc:ParameterNumeric></efac:AwardCriterionParameter></efext:EformsExtension></ext:ExtensionContent></ext:UBLExtension></ext:UBLExtensions><cbc:AwardingCriterionTypeCode listName="award-criterion-type">price</cbc:AwardingCriterionTypeCode><cbc:Name languageID="DEU">Preis</cbc:Name><cbc:Description languageID="DEU">Preis</cbc:Description></cac:SubordinateAwardingCriterion></cac:AwardingCriterion></cac:AwardingTerms><cac:AdditionalInformationParty><cac:PartyIdentification><cbc:ID schemeName="organization">ORG-0001</cbc:ID></cac:PartyIdentification></cac:AdditionalInformationParty><cac:AppealTerms><cac:PresentationPeriod><cbc:Description languageID="DEU">(1) Etwaige Vergabeverstöße muss der Bewerber/Bieter gemäß § 160 Abs. 3 Nr. 1 GWB innerhalb von 10 Tagen nach Kenntnisnahme rügen.
(2) Verstöße gegen Vergabevorschriften, die aufgrund der Bekanntmachung erkennbar sind, sind nach § 160 Abs. 3 Nr. 2 GWB spätestens bis zum Ablauf der in der Bekanntmachung benannten Frist zur Abgabe der Bewerbung oder der Angebote gegenüber dem Auftraggeber zu rügen.
(3) Verstöße gegen Vergabevorschriften, die erst in den Vergabeunterlagen erkennbar sind, sind nach § 160 Abs. 3 Nr. 3 GWB spätestens bis zum Ablauf der Frist zur Bewerbungs- oder Angebotsabgabe gegenüber dem Auftraggeber zu rügen.
(4) Ein Vergabenachprüfungsantrag ist nach § 160 Abs. 3 Nr. 4 GWB innerhalb von 15 Kalendertagen nach der Mitteilung des Auftraggebers, einer Rüge nicht abhelfen zu wollen, bei der Vergabekammer einzureichen.</cbc:Description></cac:PresentationPeriod><cac:AppealReceiverParty><cac:PartyIdentification><cbc:ID schemeName="organization">ORG-0002</cbc:ID></cac:PartyIdentification></cac:AppealReceiverParty></cac:AppealTerms></cac:TenderingTerms><cac:TenderingProcess><cbc:GovernmentAgreementConstraintIndicator>true</cbc:GovernmentAgreementConstraintIndicator><cac:AuctionTerms><cbc:AuctionConstraintIndicator>false</cbc:AuctionConstraintIndicator></cac:AuctionTerms><cac:ContractingSystem><cbc:ContractingSystemTypeCode listName="framework-agreement">none</cbc:ContractingSystemTypeCode></cac:ContractingSystem><cac:ContractingSystem><cbc:ContractingSystemTypeCode listName="dps-usage">none</cbc:ContractingSystemTypeCode></cac:ContractingSystem></cac:TenderingProcess><cac:ProcurementProject><cbc:ID>0002</cbc:ID><cbc:Name languageID="DEU">Los 2 GS und HS Pestalozzistraße und GS Bültenweg</cbc:Name><cbc:Description languageID="DEU">Die/der AN sichert die Versorgung der Grund- und Hauptschule Pestalozzistraße, Pestalozzistraße 18, 38114 Braunschweig und der Grundschule Bültenweg, Bültenweg 9, 38106 Braunschweig zu. Der Ort der Leistungserbringung sind die jeweilige Küche mit Mensa. Diese befinden sich in der Grund- und Hauptschule Pestalozzistraße im Schulgebäude. In der GS Bültenweg befinden sie sich in einem Nebengebäude.</cbc:Description><cbc:ProcurementTypeCode listName="contract-nature">services</cbc:ProcurementTypeCode><cac:ProcurementAdditionalType><cbc:ProcurementTypeCode listName="strategic-procurement">none</cbc:ProcurementTypeCode></cac:ProcurementAdditionalType><cac:MainCommodityClassification><cbc:ItemClassificationCode listName="cpv">55520000</cbc:ItemClassificationCode></cac:MainCommodityClassification><cac:RealizedLocation><cac:Address><cbc:CountrySubentityCode listName="nuts">DE911</cbc:CountrySubentityCode><cac:Country><cbc:IdentificationCode listName="country">DEU</cbc:IdentificationCode></cac:Country></cac:Address></cac:RealizedLocation><cac:ContractExtension><cbc:MaximumNumberNumeric>1</cbc:MaximumNumberNumeric><cac:Renewal><cac:Period><cbc:Description languageID="DEU">Eine Verlängerungsoption für den Zeitraum 19.08.2027 bis zum 18.07.2029 ist enthalten. Die Verlängerungsoption ist sechs Monate vor Ablauf des Vertrages durch die Stadt Braunschweig als Auftraggeberin (nachfolgend AG) zu ziehen und schriftlich mitzuteilen. Die Verlängerungsoption kann auch für einzelne Schulen in einem Los gezogen werden.</cbc:Description></cac:Period></cac:Renewal></cac:ContractExtension></cac:ProcurementProject></cac:ProcurementProjectLot><cac:ProcurementProjectLot><cbc:ID schemeName="Lot">LOT-0003</cbc:ID><cac:TenderingTerms><ext:UBLExtensions><ext:UBLExtension><ext:ExtensionContent><efext:EformsExtension><efac:StrategicProcurement><efbc:ApplicableLegalBasis listName="cvd-scope">false</efbc:ApplicableLegalBasis></efac:StrategicProcurement></efext:EformsExtension></ext:ExtensionContent></ext:UBLExtension></ext:UBLExtensions><cbc:FundingProgramCode listName="eu-funded">no-eu-funds</cbc:FundingProgramCode><cac:AwardingTerms><cac:AwardingCriterion><cac:SubordinateAwardingCriterion><ext:UBLExtensions><ext:UBLExtension><ext:ExtensionContent><efext:EformsExtension><efac:AwardCriterionParameter><efbc:ParameterCode listName="number-weight">ord-imp</efbc:ParameterCode><efbc:ParameterNumeric>1</efbc:ParameterNumeric></efac:AwardCriterionParameter></efext:EformsExtension></ext:ExtensionContent></ext:UBLExtension></ext:UBLExtensions><cbc:AwardingCriterionTypeCode listName="award-criterion-type">price</cbc:AwardingCriterionTypeCode><cbc:Name languageID="DEU">Preis</cbc:Name><cbc:Description languageID="DEU">Preis</cbc:Description></cac:SubordinateAwardingCriterion></cac:AwardingCriterion></cac:AwardingTerms><cac:AdditionalInformationParty><cac:PartyIdentification><cbc:ID schemeName="organization">ORG-0001</cbc:ID></cac:PartyIdentification></cac:AdditionalInformationParty><cac:AppealTerms><cac:PresentationPeriod><cbc:Description languageID="DEU">(1) Etwaige Vergabeverstöße muss der Bewerber/Bieter gemäß § 160 Abs. 3 Nr. 1 GWB innerhalb von 10 Tagen nach Kenntnisnahme rügen.
(2) Verstöße gegen Vergabevorschriften, die aufgrund der Bekanntmachung erkennbar sind, sind nach § 160 Abs. 3 Nr. 2 GWB spätestens bis zum Ablauf der in der Bekanntmachung benannten Frist zur Abgabe der Bewerbung oder der Angebote gegenüber dem Auftraggeber zu rügen.
(3) Verstöße gegen Vergabevorschriften, die erst in den Vergabeunterlagen erkennbar sind, sind nach § 160 Abs. 3 Nr. 3 GWB spätestens bis zum Ablauf der Frist zur Bewerbungs- oder Angebotsabgabe gegenüber dem Auftraggeber zu rügen.
(4) Ein Vergabenachprüfungsantrag ist nach § 160 Abs. 3 Nr. 4 GWB innerhalb von 15 Kalendertagen nach der Mitteilung des Auftraggebers, einer Rüge nicht abhelfen zu wollen, bei der Vergabekammer einzureichen.</cbc:Description></cac:PresentationPeriod><cac:AppealReceiverParty><cac:PartyIdentification><cbc:ID schemeName="organization">ORG-0002</cbc:ID></cac:PartyIdentification></cac:AppealReceiverParty></cac:AppealTerms></cac:TenderingTerms><cac:TenderingProcess><cbc:GovernmentAgreementConstraintIndicator>true</cbc:GovernmentAgreementConstraintIndicator><cac:AuctionTerms><cbc:AuctionConstraintIndicator>false</cbc:AuctionConstraintIndicator></cac:AuctionTerms><cac:ContractingSystem><cbc:ContractingSystemTypeCode listName="framework-agreement">none</cbc:ContractingSystemTypeCode></cac:ContractingSystem><cac:ContractingSystem><cbc:ContractingSystemTypeCode listName="dps-usage">none</cbc:ContractingSystemTypeCode></cac:ContractingSystem></cac:TenderingProcess><cac:ProcurementProject><cbc:ID>0003</cbc:ID><cbc:Name languageID="DEU">Los 3 IGS Heidberg und Gymnasium Raabeschule</cbc:Name><cbc:Description languageID="DEU">Die/der AN sichert die Versorgung der IGS Heidberg und des Gymnasiums Raabe-schule in Braunschweig zu. Der Ort der Leistungserbringung ist die Schulküche in der Stettinstraße 1, 38124 Braunschweig und der Essenausgabebereich in der Cafeteria der Raabeschule. Diese befinden sich im jeweiligen Schulgebäude auf dem gemein-sam genutzten Schulgelände.</cbc:Description><cbc:ProcurementTypeCode listName="contract-nature">services</cbc:ProcurementTypeCode><cac:ProcurementAdditionalType><cbc:ProcurementTypeCode listName="strategic-procurement">none</cbc:ProcurementTypeCode></cac:ProcurementAdditionalType><cac:MainCommodityClassification><cbc:ItemClassificationCode listName="cpv">55520000</cbc:ItemClassificationCode></cac:MainCommodityClassification><cac:RealizedLocation><cac:Address><cbc:CountrySubentityCode listName="nuts">DE911</cbc:CountrySubentityCode><cac:Country><cbc:IdentificationCode listName="country">DEU</cbc:IdentificationCode></cac:Country></cac:Address></cac:RealizedLocation><cac:ContractExtension><cbc:MaximumNumberNumeric>1</cbc:MaximumNumberNumeric><cac:Renewal><cac:Period><cbc:Description languageID="DEU">Eine Verlängerungsoption für den Zeitraum 19.08.2027 bis zum 18.07.2029 ist enthalten. Die Verlängerungsoption ist sechs Monate vor Ablauf des Vertrages durch die Stadt Braunschweig als Auftraggeberin (nachfolgend AG) zu ziehen und schriftlich mitzuteilen. Die Verlängerungsoption kann auch für einzelne Schulen in einem Los gezogen werden.</cbc:Description></cac:Period></cac:Renewal></cac:ContractExtension></cac:ProcurementProject></cac:ProcurementProjectLot><cac:TenderResult><cbc:AwardDate>2025-06-19+02:00</cbc:AwardDate></cac:TenderResult></ContractAwardNotice>